dictionary/__init__.py
dictionary/dictionary.py
d3d3_dictionary-2.0.0.dist-info/METADATA
d3d3_dictionary-2.0.0.dist-info/WHEEL
d3d3_dictionary-2.0.0.dist-info/top_level.txt
d3d3_dictionary-2.0.0.dist-info/RECORD
